pepper/__init__.py
pepper/cli.py
pepper/exceptions.py
pepper/libpepper.py
pepper/retcode.py
pepper/script.py
salt_pepper-0.7.6.data/scripts/pepper
salt_pepper-0.7.6.dist-info/LICENSE
salt_pepper-0.7.6.dist-info/METADATA
salt_pepper-0.7.6.dist-info/WHEEL
salt_pepper-0.7.6.dist-info/top_level.txt
salt_pepper-0.7.6.dist-info/RECORD
