Metadata-Version: 2.1
Name: salt-pepper
Version: 0.7.6
Summary: A CLI front-end to a running salt-api system
Home-page: http://saltstack.com
Author: Seth House
Author-email: shouse@saltstack.com
License: UNKNOWN
Platform: UNKNOWN
Classifier: Programming Language :: Python
Classifier: Programming Language :: Cython
Classifier: Programming Language :: Python :: 2.7
Classifier: Programming Language :: Python :: 3.4
Classifier: Programming Language :: Python :: 3.5
Classifier: Programming Language :: Python :: 3.6
Classifier: Development Status :: 5 - Production/Stable
Classifier: Environment :: Console
Classifier: Intended Audience :: Developers
Classifier: Intended Audience :: Information Technology
Classifier: Intended Audience :: System Administrators
Classifier: License :: OSI Approved :: Apache Software License
Classifier: Operating System :: POSIX :: Linux
Classifier: Topic :: System :: Clustering
Classifier: Topic :: System :: Distributed Computing
Provides-Extra: kerberos
